media_manipulator/__init__.py
media_manipulator/cli.py
media_manipulator/core/__init__.py
media_manipulator/core/interpreter.py
media_manipulator/core/processor.py
media_manipulator/core/strategy_registry.py
media_manipulator/core/strategies/__init__.py
media_manipulator/core/strategies/add.py
media_manipulator/core/strategies/base.py
media_manipulator/core/strategies/clip.py
media_manipulator/core/strategies/concat.py
media_manipulator/core/strategies/overlay.py
media_manipulator/utils/__init__.py
media_manipulator/utils/audio.py
media_manipulator/utils/helpers.py
media_manipulator/utils/image.py
media_manipulator/utils/logger.py
media_manipulator/utils/video.py
media_manipulator_lib-0.1.5.dist-info/licenses/LICENSE
media_manipulator_lib-0.1.5.dist-info/METADATA
media_manipulator_lib-0.1.5.dist-info/WHEEL
media_manipulator_lib-0.1.5.dist-info/top_level.txt
media_manipulator_lib-0.1.5.dist-info/RECORD
