Metadata-Version: 2.4
Name: media-manipulator-lib
Version: 0.1.5
Summary: A composable FFmpeg-based video editing library
Author: Aditya Sharma
Author-email: aditya.3sharma@angelone.in
Classifier: Programming Language :: Python :: 3
Classifier: Operating System :: OS Independent
Requires-Python: >=3.8
License-File: LICENSE
Requires-Dist: ffmpeg-python
Requires-Dist: colorlog
Dynamic: author
Dynamic: author-email
Dynamic: classifier
Dynamic: description
Dynamic: description-content-type
Dynamic: license-file
Dynamic: requires-dist
Dynamic: requires-python
Dynamic: summary
